boruta_surv/__init__.py
boruta_surv/boruta_surv.py
boruta_surv-0.1.0.dist-info/METADATA
boruta_surv-0.1.0.dist-info/WHEEL
boruta_surv-0.1.0.dist-info/top_level.txt
boruta_surv-0.1.0.dist-info/RECORD
