Metadata-Version: 2.1
Name: boruta-surv
Version: 0.1.0
Summary: Feature Selection for Survival Analysis using Boruta
Home-page: https://github.com/alterreal/boruta-surv
Author: Alexandre Calado
Author-email: alexandreluiscalado@gmail.com
Classifier: Programming Language :: Python :: 3
Classifier: License :: OSI Approved :: MIT License
Classifier: Operating System :: OS Independent
Requires-Python: >=3.7
Requires-Dist: numpy
Requires-Dist: pandas
Requires-Dist: scipy
Requires-Dist: scikit-learn
Requires-Dist: scikit-survival
Requires-Dist: seaborn
Requires-Dist: matplotlib
